XSpect_EW.py
xspect_ew-1.0.1.dist-info/WHEEL
xspect_ew-1.0.1.dist-info/METADATA
xspect_ew-1.0.1.dist-info/RECORD
