Metadata-Version: 2.1
Name: XSpect-EW
Version: 1.0.1
Summary: Python3 - User guided equivalent wideth measurement and analysis tool for stellar absorption spectra 
Author-email: George Vejar <forgeousgeorge@gmail.com>
Requires-Python: >=3.5
Classifier: License :: OSI Approved :: MIT License
Requires-Dist: numpy >=1.2
Requires-Dist: matplotlib >=3.4
Requires-Dist: scipy >=1.6
Requires-Dist: astropy >=4.0
Requires-Dist: george >=0.4
Project-URL: Home, https://github.com/forgeousgeorge/XSpect
